common/__init__.py
common/crc.py
common/dispatcher.py
common/event.py
common/protocol.py
common/state.py
common/utils.py
common/video_stream.py
tello_ctrl-1.0.6.dist-info/License.txt
tello_ctrl-1.0.6.dist-info/METADATA
tello_ctrl-1.0.6.dist-info/WHEEL
tello_ctrl-1.0.6.dist-info/top_level.txt
tello_ctrl-1.0.6.dist-info/RECORD
