Metadata-Version: 2.1
Name: tello-ctrl
Version: 1.0.6
Project-URL: Issues, https://github.com/sebdelp/tello-control/issues
Project-URL: Repository, https://github.com/sebdelp/tello-control
Keywords: tello,drone,Control,low level protocol,dji
Classifier: Programming Language :: Python :: 3
Classifier: Intended Audience :: Developers
Classifier: Operating System :: Microsoft :: Windows
Classifier: Development Status :: 3 - Alpha
Classifier: License :: OSI Approved :: Apache Software License
License-File: License.txt
Requires-Dist: av
Requires-Dist: pillow
Requires-Dist: opencv-python
